<?xml version = '1.0' encoding = 'UTF-8'?>
<Entity class="oracle.dbtools.crest.model.design.logical.Entity" id="10E0E96C-6CF8-618B-507B-A027D4EDFE5E" directorySegmentName="seg_0" name="ESPECIALIZACION">
<createdBy>Jonas</createdBy>
<createdTime>2016-12-02 15:30:47 UTC</createdTime>
<generatorID>103CE299-C604-4BA4-EA06-1FF084BB1279</generatorID>
<ownerDesignName>Modelado</ownerDesignName>
<engineerTo>
<item key="70643189-CB65-1418-B13A-F9A0682DC28A" value="true"/>
</engineerTo>
<pkName>ESPECIALIZACION PK</pkName>
<adequatelyNormalized>NO</adequatelyNormalized>
<expectedVolumes>0</expectedVolumes>
<fwdEngineeringStrategyName>Single Table</fwdEngineeringStrategyName>
<growthPercent>0</growthPercent>
<growthType>Year</growthType>
<maxVolumes>9999999</maxVolumes>
<minVolumes>0</minVolumes>
<normalForm>Third</normalForm>
<fonts>
<FontObject class="oracle.dbtools.crest.model.design.FontObjectWr">
<foType>Título</foType>
<fontStyle>1</fontStyle>
<colorRGB>-16776961</colorRGB>
</FontObject>
<FontObject class="oracle.dbtools.crest.model.design.FontObjectWr">
<foType>Atributo</foType>
<colorRGB>-16777216</colorRGB>
</FontObject>
<FontObject class="oracle.dbtools.crest.model.design.FontObjectWr">
<foType>Tipo de Dato</foType>
<colorRGB>-16744448</colorRGB>
</FontObject>
<FontObject class="oracle.dbtools.crest.model.design.FontObjectWr">
<foType>Elemento de Clave Primaria</foType>
<colorRGB>-16776961</colorRGB>
</FontObject>
<FontObject class="oracle.dbtools.crest.model.design.FontObjectWr">
<foType>Elemento de Clave Ajena</foType>
<colorRGB>-16777216</colorRGB>
</FontObject>
<FontObject class="oracle.dbtools.crest.model.design.FontObjectWr">
<foType>Elemento de Clave Única</foType>
<colorRGB>-16776961</colorRGB>
</FontObject>
<FontObject class="oracle.dbtools.crest.model.design.FontObjectWr">
<foType>No Nulo</foType>
<colorRGB>-65536</colorRGB>
</FontObject>
<FontObject class="oracle.dbtools.crest.model.design.FontObjectWr">
<foType>Clave</foType>
<colorRGB>-16777216</colorRGB>
</FontObject>
</fonts>
<attributes>
<Attribute class="oracle.dbtools.crest.model.design.logical.Attribute" name="NOMBRE" id="0568324C-14EF-D3F9-8F14-1A082DADE4A5">
<createdBy>Jonas</createdBy>
<createdTime>2016-12-02 15:30:47 UTC</createdTime>
<generatorID>32EF65B6-0587-782F-88CD-BED9534C706E</generatorID>
<ownerDesignName>Modelado</ownerDesignName>
<engineerTo>
<item key="70643189-CB65-1418-B13A-F9A0682DC28A" value="true"/>
</engineerTo>
<useDomainConstraints>false</useDomainConstraints>
<use>1</use>
<logicalDatatype>LOGDT024</logicalDatatype>
<dataTypeSize>30 BYTE</dataTypeSize>
</Attribute>
<Attribute class="oracle.dbtools.crest.model.design.logical.Attribute" name="DESCRIPCION" id="F4F69137-81D3-8100-49C8-D4944E5CE546">
<createdBy>Jonas</createdBy>
<createdTime>2016-12-02 15:30:47 UTC</createdTime>
<generatorID>EF9F2691-6E39-C191-3C36-770FCFEE7701</generatorID>
<ownerDesignName>Modelado</ownerDesignName>
<engineerTo>
<item key="70643189-CB65-1418-B13A-F9A0682DC28A" value="true"/>
</engineerTo>
<useDomainConstraints>false</useDomainConstraints>
<use>1</use>
<logicalDatatype>LOGDT024</logicalDatatype>
<dataTypeSize>100 BYTE</dataTypeSize>
</Attribute>
</attributes>
<identifiers>
<identifier class="oracle.dbtools.crest.model.design.logical.CandidateKey" id="94E6FCBD-F302-8DDB-930F-3AD286A4622F" name="ESPECIALIZACION PK">
<createdBy>Jonas</createdBy>
<createdTime>2016-12-02 15:30:47 UTC</createdTime>
<generatorID>E8351C2E-1CBA-EAD0-9DCC-1A1E34629BDD</generatorID>
<ownerDesignName>Modelado</ownerDesignName>
<engineerTo>
<item key="70643189-CB65-1418-B13A-F9A0682DC28A" value="true"/>
</engineerTo>
<pk>true</pk>
<usedAttributes>
<attributeRef>0568324C-14EF-D3F9-8F14-1A082DADE4A5</attributeRef>
</usedAttributes>
</identifier>
</identifiers>
</Entity>